solve_ps/main.py
solve_ps/subs/diff.py
solve_ps/subs/get.py
solve_ps/subs/run.py
solve_ps/subs/tc.py
solve_ps-0.1.4.dist-info/METADATA
solve_ps-0.1.4.dist-info/WHEEL
solve_ps-0.1.4.dist-info/entry_points.txt
solve_ps-0.1.4.dist-info/licenses/LICENSE
solve_ps-0.1.4.dist-info/RECORD
